wrapper_redis_client/__init__.py
wrapper_redis_client/exceptions.py
wrapper_redis_client/redis_db.py
wrapper_redis_client-0.0.4.dist-info/LICENSE
wrapper_redis_client-0.0.4.dist-info/METADATA
wrapper_redis_client-0.0.4.dist-info/WHEEL
wrapper_redis_client-0.0.4.dist-info/top_level.txt
wrapper_redis_client-0.0.4.dist-info/RECORD
