Metadata-Version: 2.1
Name: wrapper-redis-client
Version: 0.0.4
Summary: Wrapper for Redis Client
Home-page: UNKNOWN
Author: Tatianno Alves
Author-email: tferreiraalves@gmail.com
License: MIT License
Keywords: wrapper redis client
Platform: UNKNOWN
Requires-Dist: redis
Requires-Dist: wheel
